text2pic4ai/__init__.py
text2pic4ai/_freetype/__init__.py
text2pic4ai/_freetype/freetype.py
text2pic4ai/_huggingface/__init__.py
text2pic4ai/_huggingface/processor.py
text2pic4ai/_huggingface/pyarrow_io.py
"text2pic4ai/_pkg_data/Noto_Sans/NotoSans-Italic-VariableFont_wdth,wght.ttf"
"text2pic4ai/_pkg_data/Noto_Sans/NotoSans-VariableFont_wdth,wght.ttf"
text2pic4ai/_pkg_data/Noto_Sans/OFL.txt
text2pic4ai/_pkg_data/Noto_Sans/README.txt
text2pic4ai/_pkg_data/Noto_Sans_JP/NotoSansJP-VariableFont_wght.ttf
text2pic4ai/_pkg_data/Noto_Sans_JP/OFL.txt
text2pic4ai/_pkg_data/Noto_Sans_JP/README.txt
text2pic4ai/_pkg_data/Noto_Sans_KR/NotoSansKR-VariableFont_wght.ttf
text2pic4ai/_pkg_data/Noto_Sans_KR/OFL.txt
text2pic4ai/_pkg_data/Noto_Sans_KR/README.txt
text2pic4ai/_pkg_data/Noto_Sans_SC/NotoSansSC-VariableFont_wght.ttf
text2pic4ai/_pkg_data/Noto_Sans_SC/OFL.txt
text2pic4ai/_pkg_data/Noto_Sans_SC/README.txt
text2pic4ai/_pkg_data/Noto_Sans_TC/NotoSansTC-VariableFont_wght.ttf
text2pic4ai/_pkg_data/Noto_Sans_TC/OFL.txt
text2pic4ai/_pkg_data/Noto_Sans_TC/README.txt
text2pic4ai/_pkg_data/__init__.py
text2pic4ai/_pkg_data/pkg_data.py
text2pic4ai/_pkg_data/sample.txt
text2pic4ai/cli/__init__.py
text2pic4ai/cli/preview_dataset.py
text2pic4ai/cli/run_render_dataset.py
text2pic4ai/py.typed
text2pic4ai-0.0.1.dist-info/LICENSE
text2pic4ai-0.0.1.dist-info/METADATA
text2pic4ai-0.0.1.dist-info/WHEEL
text2pic4ai-0.0.1.dist-info/RECORD
